<xml version="1.0">
<dashboard>
	<widget field="autoReset" type="Boolean" class="edu.wpi.first.smartdashboard.gui.elements.TextBox">
		<location x="151" y="21"/>
	</widget>
	<widget field="Pose" type="String" class="edu.wpi.first.smartdashboard.gui.elements.TextBox">
		<location x="151" y="0"/>
	</widget>
	<widget field="Gyro" type="Number" class="edu.wpi.first.smartdashboard.gui.elements.TextBox">
		<location x="41" y="0"/>
	</widget>
	<widget field="optimize" type="Boolean" class="edu.wpi.first.smartdashboard.gui.elements.TextBox">
		<location x="0" y="476"/>
	</widget>
	<widget field="FR" type="String" class="edu.wpi.first.smartdashboard.gui.elements.TextBox">
		<location x="0" y="455"/>
	</widget>
	<widget field="FL" type="String" class="edu.wpi.first.smartdashboard.gui.elements.TextBox">
		<location x="0" y="434"/>
	</widget>
	<widget field="BL" type="String" class="edu.wpi.first.smartdashboard.gui.elements.TextBox">
		<location x="0" y="56"/>
	</widget>
	<widget field="BR" type="String" class="edu.wpi.first.smartdashboard.gui.elements.TextBox">
		<location x="0" y="35"/>
	</widget>
	<static-widget class="edu.wpi.first.smartdashboard.gui.elements.ConnectionIndicator">
		<location x="17" y="11"/>
		<width>23</width>
		<height>23</height>
	</static-widget>
	<static-widget class="edu.wpi.first.smartdashboard.gui.elements.ConnectionIndicator">
		<location x="17" y="11"/>
		<width>23</width>
		<height>23</height>
	</static-widget>
	<static-widget class="edu.wpi.first.smartdashboard.gui.elements.ConnectionIndicator">
		<location x="17" y="11"/>
		<width>23</width>
		<height>23</height>
	</static-widget>
	<static-widget class="edu.wpi.first.smartdashboard.gui.elements.ConnectionIndicator">
		<location x="17" y="11"/>
		<width>23</width>
		<height>23</height>
	</static-widget>
	<static-widget class="edu.wpi.first.smartdashboard.gui.elements.ConnectionIndicator">
		<location x="17" y="11"/>
		<width>23</width>
		<height>23</height>
	</static-widget>
	<static-widget class="edu.wpi.first.smartdashboard.gui.elements.CameraServerViewer">
		<location x="21" y="100"/>
		<width>356</width>
		<height>301</height>
		<property name="Camera Choice" value="testCamera"/>
	</static-widget>
</dashboard>
<live-window>
</live-window>
	<hidden field="Field"/>
</xml>